claudecraft/__init__.py
claudecraft-1.0.2.dist-info/licenses/LICENSE
claudecraft-1.0.2.dist-info/METADATA
claudecraft-1.0.2.dist-info/WHEEL
claudecraft-1.0.2.dist-info/entry_points.txt
claudecraft-1.0.2.dist-info/top_level.txt
claudecraft-1.0.2.dist-info/RECORD
