Metadata-Version: 2.4
Name: claudecraft
Version: 1.0.2
Summary: Multi-Agent Development Framework for High-Quality, Secure Software Development with Claude AI
Author-email: ClaudeCraft Team <hello@claudecraft.dev>
Maintainer-email: ClaudeCraft Team <hello@claudecraft.dev>
License: MIT
Project-URL: Homepage, https://github.com/stack-junkie/ClaudeCraft
Project-URL: Documentation, https://github.com/stack-junkie/ClaudeCraft#readme
Project-URL: Repository, https://github.com/stack-junkie/ClaudeCraft.git
Project-URL: Bug Tracker, https://github.com/stack-junkie/ClaudeCraft/issues
Keywords: claude,ai,framework,development,multi-agent,security,quality,template,react,python,nodejs,automation,workflow
Classifier: Development Status :: 5 - Production/Stable
Classifier: Intended Audience :: Developers
Classifier: License :: OSI Approved :: MIT License
Classifier: Operating System :: OS Independent
Classifier: Programming Language :: Python :: 3
Classifier: Programming Language :: Python :: 3.8
Classifier: Programming Language :: Python :: 3.9
Classifier: Programming Language :: Python :: 3.10
Classifier: Programming Language :: Python :: 3.11
Classifier: Programming Language :: Python :: 3.12
Classifier: Topic :: Software Development :: Libraries :: Application Frameworks
Classifier: Topic :: Software Development :: Code Generators
Classifier: Topic :: Scientific/Engineering :: Artificial Intelligence
Requires-Python: >=3.8
License-File: LICENSE
Dynamic: license-file
